odoo/addons/fieldservice_route_stock/README.rst
odoo/addons/fieldservice_route_stock/__init__.py
odoo/addons/fieldservice_route_stock/__manifest__.py
odoo/addons/fieldservice_route_stock/i18n/es.po
odoo/addons/fieldservice_route_stock/i18n/es_CL.po
odoo/addons/fieldservice_route_stock/i18n/fieldservice_route_stock.pot
odoo/addons/fieldservice_route_stock/models/__init__.py
odoo/addons/fieldservice_route_stock/models/fsm_route.py
odoo/addons/fieldservice_route_stock/models/fsm_route_dayroute.py
odoo/addons/fieldservice_route_stock/models/stock_inventory.py
odoo/addons/fieldservice_route_stock/readme/CONTRIBUTORS.rst
odoo/addons/fieldservice_route_stock/readme/CREDITS.rst
odoo/addons/fieldservice_route_stock/readme/DESCRIPTION.rst
odoo/addons/fieldservice_route_stock/readme/USAGE.rst
odoo/addons/fieldservice_route_stock/static/description/icon.png
odoo/addons/fieldservice_route_stock/static/description/index.html
odoo/addons/fieldservice_route_stock/tests/__init__.py
odoo/addons/fieldservice_route_stock/tests/test_fieldservice_route_stock.py
odoo/addons/fieldservice_route_stock/views/fsm_route.xml
odoo/addons/fieldservice_route_stock/views/fsm_route_dayroute.xml
odoo12_addon_fieldservice_route_stock-12.0.1.2.1.dist-info/METADATA
odoo12_addon_fieldservice_route_stock-12.0.1.2.1.dist-info/WHEEL
odoo12_addon_fieldservice_route_stock-12.0.1.2.1.dist-info/top_level.txt
odoo12_addon_fieldservice_route_stock-12.0.1.2.1.dist-info/RECORD
